duckdb_selective_search/cache.py
duckdb_selective_search/pt.py
duckdb_selective_search/retriever.py
duckdb_selective_search/util.py
duckdb_selective_search-0.0.1.dist-info/METADATA
duckdb_selective_search-0.0.1.dist-info/WHEEL
duckdb_selective_search-0.0.1.dist-info/RECORD
